pycascades/__init__.py
pycascades/amazon_rainforest/__init__.py
pycascades/amazon_rainforest/r_crit_unstable_amazon.py
pycascades/amazon_rainforest/amazon_code/__init__.py
pycascades/amazon_rainforest/amazon_code/amazon.py
pycascades/amazon_rainforest/amazon_code/functions_amazon.py
pycascades/amazon_rainforest/data/__init__.py
pycascades/amazon_rainforest/evaluations/__init__.py
pycascades/amazon_rainforest/evaluations/r_crit_risk_maps.py
pycascades/amazon_rainforest/results/__init__.py
pycascades/amazon_rainforest/results/no_coupling/__init__.py
pycascades/earth_system/Main_earth_system.py
pycascades/earth_system/__init__.py
pycascades/earth_system/earth_sys/__init__.py
pycascades/earth_system/earth_sys/earth.py
pycascades/earth_system/earth_sys/functions_earth_system.py
pycascades/earth_system/earth_sys/timing.py
pycascades/earth_system/earth_sys/tipping_network_earth_system.py
pycascades/earth_system/evaluations/__init__.py
pycascades/earth_system/evaluations/tipped_elements.py
pycascades/earth_system/evaluations/tipped_elements_plots.py
pycascades/earth_system/evaluations/plots/__init__.py
pycascades/earth_system/lhs_preparator/__init__.py
pycascades/earth_system/lhs_preparator/latin_probability_distribution.py
pycascades/earth_system/results/__init__.py
pycascades/earth_system/results/feedbacks/__init__.py
pycascades/examples/__init__.py
pycascades/examples/economic_cascade.py
pycascades/examples/example_cusp_hopf.py
pycascades/examples/example_cusp_noise.py
pycascades/examples/network_tipping_cascades_plot.py
pycascades/examples/network_types_plot.py
pycascades/examples/tutorial.py
pycascades/modules/__init__.py
pycascades/modules/core/__init__.py
pycascades/modules/core/coupling.py
pycascades/modules/core/coupling_economic.py
pycascades/modules/core/evolve.py
pycascades/modules/core/evolve_economic.py
pycascades/modules/core/evolve_sde.py
pycascades/modules/core/tipping_element.py
pycascades/modules/core/tipping_element_economic.py
pycascades-1.0.1.dist-info/LICENSE.rst
pycascades-1.0.1.dist-info/METADATA
pycascades-1.0.1.dist-info/WHEEL
pycascades-1.0.1.dist-info/top_level.txt
pycascades-1.0.1.dist-info/RECORD
