Metadata-Version: 2.1
Name: pycascades
Version: 1.0.1
Summary: PyCascades: Simulating tipping cascades on complex networks
Home-page: https://zenodo.org/record/4153102#.X8DMhMIo9H4
Author: Jonathan Krönke, Nico Wunderling, Jonathan Donges
Author-email: nico.wunderling@pik-potsdam.de
License: UNKNOWN
Platform: UNKNOWN
Classifier: Programming Language :: Python :: 3
Classifier: License :: OSI Approved :: MIT License
Classifier: Operating System :: OS Independent
Requires-Python: >=3.6
